gfflu/__about__.py
gfflu/__init__.py
gfflu/annotation.py
gfflu/blastx.py
gfflu/cli.py
gfflu/io.py
gfflu/miniprot.py
gfflu/peptides.py
gfflu/data/iav-annotation.faa
gfflu/data/iav-annotation.faa.pdb
gfflu/data/iav-annotation.faa.phr
gfflu/data/iav-annotation.faa.pin
gfflu/data/iav-annotation.faa.pjs
gfflu/data/iav-annotation.faa.psq
gfflu/data/iav-annotation.faa.ptf
gfflu/data/iav-annotation.faa.pto
gfflu/gene_segments/__init__.py
gfflu/gene_segments/segment_2_pb1.py
gfflu/gene_segments/segment_4_ha.py
gfflu-0.0.2.dist-info/METADATA
gfflu-0.0.2.dist-info/WHEEL
gfflu-0.0.2.dist-info/entry_points.txt
gfflu-0.0.2.dist-info/licenses/LICENSE.txt
gfflu-0.0.2.dist-info/RECORD
