Metadata-Version: 2.1
Name: gfflu
Version: 0.0.2
Summary: Annotate Influenza A virus gene segment sequences and output GFF3 files.
Project-URL: Documentation, https://github.com/CFIA-NCFAD/gfflu#readme
Project-URL: Issues, https://github.com/CFIA-NCFAD/gfflu/issues
Project-URL: Source, https://github.com/CFIA-NCFAD/gfflu
Author-email: Peter Kruczkiewicz <peter.kruczkiewicz@gmail.com>
License-Expression: MIT
License-File: LICENSE.txt
Classifier: Development Status :: 4 - Beta
Classifier: Programming Language :: Python
Classifier: Programming Language :: Python :: 3
Classifier: Programming Language :: Python :: 3 :: Only
Classifier: Programming Language :: Python :: 3.8
Classifier: Programming Language :: Python :: 3.9
Classifier: Programming Language :: Python :: 3.10
Classifier: Programming Language :: Python :: 3.11
Classifier: Programming Language :: Python :: Implementation :: CPython
Requires-Python: >=3.8
Requires-Dist: bcbio-gff
Requires-Dist: biopython
Requires-Dist: polars
Requires-Dist: rich
Requires-Dist: typer
